a2_legacy_launcher/LegacyDev.keystore
a2_legacy_launcher/__main__.py
a2_legacy_launcher/aapt2-ARM64
a2_legacy_launcher/apktool-2.12.1-termux.jar
a2_legacy_launcher/apktool_2.12.0.jar
a2_legacy_launcher-1.3.5.dist-info/licenses/LICENSE
a2_legacy_launcher-1.3.5.dist-info/METADATA
a2_legacy_launcher-1.3.5.dist-info/WHEEL
a2_legacy_launcher-1.3.5.dist-info/entry_points.txt
a2_legacy_launcher-1.3.5.dist-info/top_level.txt
a2_legacy_launcher-1.3.5.dist-info/RECORD
