Metadata-Version: 2.4
Name: a2-legacy-launcher
Version: 1.3.5
Summary: An integrated version manager for Oculus/Unreal games
Author-email: Obelous <1@obelous.dev>
License-Expression: MIT
Requires-Python: >=3.8
License-File: LICENSE
Requires-Dist: requests
Requires-Dist: colorama
Requires-Dist: pySmartDL
Requires-Dist: pyyaml
Dynamic: license-file
